sentientis/__init__.py
sentientis/agents/__init__.py
sentientis/agents/abstractions.py
sentientis/agents/core.py
sentientis/algorithms/__init__.py
sentientis/algorithms/abstractions.py
sentientis/algorithms/core.py
sentientis/envs/__init__.py
sentientis/envs/abstractions/__init__.py
sentientis/envs/core/__init__.py
sentientis/main/__init__.py
sentientis/main/run.py
sentientis-0.0.1.dist-info/METADATA
sentientis-0.0.1.dist-info/WHEEL
sentientis-0.0.1.dist-info/RECORD
