Metadata-Version: 2.1
Name: sentientis
Version: 0.0.1
Summary: The framework
License: BSD-3
Author: RenChu Wang
Author-email: patrick1031wang@gmail.com
Requires-Python: >=3.10,<4.0
Classifier: License :: Other/Proprietary License
Classifier: Programming Language :: Python :: 3
Classifier: Programming Language :: Python :: 3.10
Classifier: Programming Language :: Python :: 3.11
Requires-Dist: gymnasium (>=0.28.1,<0.29.0)
Requires-Dist: hydra-core (>=1.3.2,<2.0.0)
Requires-Dist: omegaconf (>=2.3.0,<3.0.0)
Requires-Dist: torch (>=2.0.1,<3.0.0)
